Workbook

Sheet ORCAMENTOS
A1: RELATÓRIO ORCAMENTOS
A10: DATA | B10: Nº DE ORÇA | C10: REV. | D10: INSTALADOR | E10: NOME DA OBRA | F10: TIPO DE OBRA | G10: VENDEDOR | H10: CONTATO | I10: VALOR BRUTO | J10: COMISSÃO | K10: M2 | L10: PRIORIDADE | M10: STATUS | N10: CONCORRENTE | O10: MOTIVO | P10: VALOR CONCORRENTE | Q10: PROJETISTA | R10: ESPECIFICAÇÕES | U10: COMISSÃO 10mm | W10: VALOR
A11: 45660 | B11: 1 | D11: KEEVA TEIC | E11: - | G11: Michel | H11: Rachel | I11: 3411.11 | K11: 24 | L11: FECHADO | N11: - | P11: - | Q11: - | R11: - | U11: 0.07 | V11: - | W11: 148.05 | X11: a | Y11: 164.5
A12: 45663 | B12: 2 | D12: SOLAR AR | E12: HOSPITAL DE REGISTRO - SIRIO LIBANES - DUTOS CENTRO CIRURGICO | G12: Michel | H12: Claudenir | I12: 8092.7 | K12: 96 | L12: FECHADO | N12: - | P12: - | Q12: - | R12: - | U12: 0.06 | V12: - | W12: 144.82 | X12: a | Y12: 148.04
A13: 45663 | B13: 3 | D13: INOVECTOR | E13: HOSP. MORUMBI_SADT | G13: Fernando | H13: Eliete | I13: 14294.94 | K13: 192 | L13: FECHADO | N13: - | P13: - | Q13: - | R13: - | U13: 0.05 | V13: - | W13: 134.64 | X13: a | Y13: 144.81
A14: 45663 | B14: 4 | D14: REWELL OTAVIO | E14: ENG BRUNO NY TOWER | G14: Gabriel | H14: Rewell | I14: 2259.26 | K14: 24 | L14: CANCELADO | N14: - | P14: - | Q14: - | R14: - | U14: 0.04 | V14: - | W14: 125.83 | X14: a | Y14: 134.63
A15: 45663 | B15: 5 | D15: INOVECTOR | E15: VILLA LOBOS - REQ 2.04 | G15: Fernando | H15: Cristina | I15: 6933.2 | K15: 96 | L15: FECHADO | N15: - | P15: - | Q15: - | R15: - | U15: 0.03 | V15: - | W15: 118.08 | X15: a | Y15: 125.82
A16: 45663 | B16: 6 | D16: REWELL OTAVIO | E16: RESIDENCIA UNIFAMILIAR - FERNANDO PORTOLANI DE ANDRADE | G16: Gabriel | H16: Rewell | I16: 9106.66 | K16: 72 | L16: CANCELADO | N16: - | P16: - | Q16: COLD SPACE | R16: CHAPA DE ACO GALVANIZADO | U16: 0.02 | V16: - | W16: 111.24 | X16: a | Y16: 118.07
A17: 45663 | B17: 7 | D17: REWELL OTAVIO | E17: SALA 104 - NY TOWER - ARACATUBA - SP | G17: Gabriel | H17: Rewell | I17: 26029.3 | K17: 240 | L17: CANCELADO | N17: - | P17: - | Q17: COLD SPACE | R17: CHAPA DE ACO GALVANIZADO
A18: 45663 | B18: 8 | D18: GRUPO R1 | E18: - | G18: Gabriel | H18: Janaina | I18: 3232.69 | K18: - | L18: CANCELADO | M18: Negociando | N18: - | P18: - | Q18: - | R18: -
A19: 45663 | B19: 9 | D19: AWA AR CONDICIONADO | E19: ATACADAO - LAURO DE FREITAS CAJI - BA | G19: Guilherme | H19: Maria Julia | I19: 175342.6 | K19: 1752 | L19: CANCELADO | N19: - | P19: - | Q19: ARCO + | R19: N/E | U19: COMISSÃO 20mm | W19: VALOR
A20: 45663 | B20: 10 | D20: CONSTARCO | E20: - | G20: Fernando | H20: Fabricio | I20: 297411.92 | K20: 3408 | L20: CANCELADO | M20: PERDERAM A OBRA | N20: - | P20: - | Q20: - | R20: - | U20: 0.07 | V20: - | W20: 181.58 | X20: a | Y20: 201.76
A21: 45663 | B21: 11 | D21: INOVECTOR | E21: ANALIA FRANCO - REQ 2.03 | G21: Fernando | H21: Eliete | I21: 9352.59 | K21: 144 | L21: FECHADO | N21: - | P21: - | Q21: - | R21: - | U21: 0.06 | V21: - | W21: 177.86 | X21: a | Y21: 181.57
A22: 45663 | B22: 12 | D22: INOVECTOR | E22: HOSP.OSASCO - REQ 2.04 | G22: Fernando | H22: Cristina | I22: 169.83 | K22: - | L22: CANCELADO | N22: - | P22: - | Q22: - | R22: - | U22: 0.05 | V22: - | W22: 165.39 | X22: a | Y22: 177.85
A23: 45663 | B23: 13 | D23: AIR SUPPLY | E23: ASSAI ATACADISTA - SJRP PALESTRA - RENOVACAO | G23: Gabriel | H23: Pedro | I23: 51413.93 | K23: 624 | L23: CANCELADO | N23: - | P23: - | Q23: PLANENRAC | R23: N/E | U23: 0.04 | V23: - | W23: 154.54 | X23: a | Y23: 165.38
A24: 45664 | B24: 14 | D24: GSA DUTOS | E24: - | G24: Gabriel | H24: Geraldo | I24: 835.52 | K24: 4.8 | L24: CANCELADO | N24: - | P24: - | Q24: - | R24: - | U24: 0.03 | V24: - | W24: 145.03 | X24: a | Y24: 154.53
A25: 45664 | B25: 15 | D25: CATELAN | E25: - | G25: Gabriel | H25: Priscila | I25: 2024.86 | K25: 26.4 | L25: CANCELADO | M25: Apenas consulta | N25: - | P25: - | Q25: - | R25: - | U25: 0.02 | V25: - | W25: 136.61 | X25: a | Y25: 145.02
A26: 45664 | B26: 16 | D26: DUCTBUSTERS | E26: - | G26: Michel | H26: Camila | I26: 947.84 | K26: - | L26: FECHADO | N26: - | P26: - | Q26: - | R26: -
A27: 45664 | B27: 17 | D27: AIRPLAN | E27: SHOPPING CENTER - MISTRAL - JK IGUATEMI | G27: Gabriel | H27: Laercio | I27: 8557.66 | K27: 96 | L27: CANCELADO | N27: - | P27: - | Q27: FORTIORE SP | R27: MPU
A28: 45664 | B28: 18 | D28: CIVIL AR | E28: THYSSENKRUPP - POÇOS DE CALDAS - MG | G28: Fernando | H28: Atila | I28: 12090.52 | K28: 912 | L28: FECHADO | M28: Aguardando aprovação | N28: - | P28: - | Q28: CIVIL AR | R28: MPU | U28: COMISSÃO 30mm | W28: VALOR
A29: 45664 | B29: 19 | D29: EKO CLIMAX | E29: - | G29: Michel | H29: Rogerio | I29: 8569.14 | K29: 72 | L29: FECHADO | N29: - | P29: - | Q29: - | R29: - | U29: 0.07 | V29: - | W29: 337.68 | X29: a | Y29: 375.2
A30: 45664 | B30: 20 | D30: FAZENG | E30: CLÍNICA PAULISTA - 13º ANDAR - BELA VISTA - SP | G30: Gabriel | H30: Andrey | I30: 15600.04 | K30: 144 | L30: CANCELADO | M30: Aguardando aprovação | N30: - | P30: - | Q30: FEZENG | R30: N/E | U30: 0.06 | V30: - | W30: 328.72 | X30: a | Y30: 337.67
A31: 45664 | B31: 21 | D31: HELP AIR | E31: - | G31: Gabriel | H31: Joyce | I31: 2288.37 | K31: 24 | L31: CANCELADO | N31: - | P31: - | Q31: - | R31: - | U31: 0.05 | V31: - | W31: 305.64 | X31: a | Y31: 328.71
A32: 45664 | B32: 22 | D32: DUTOLEVE | E32: GESTAMP - TATUAPE - SP | G32: Gabriel | H32: Newton | I32: 4668.85 | K32: 48 | L32: CANCELADO | N32: - | P32: - | Q32: MLF ENGENHARIA | R32: N/E | U32: 0.04 | V32: - | W32: 285.59 | X32: a | Y32: 305.63
A33: 45664 | B33: 23 | D33: AMS INSTALACOES | E33: COMPER - BELVEDERE | G33: Gabriel | H33: Almir | I33: 86323.42 | K33: 1200 | L33: FECHADO | M33: - | N33: - | O33: - | P33: - | Q33: - | R33: - | U33: 0.03 | V33: - | W33: 268.02 | X33: a | Y33: 285.58
A34: 45665 | B34: 24 | D34: INTEG ENGENHARIA | E34: - | G34: Fernando | H34: Angela | I34: 16406.46 | K34: - | L34: PERDIDO | M34: MULTIVAC - COND PGTO | N34: MULTIVAC | O34: COND. PGTO | P34: - | Q34: - | R34: - | U34: 0.02 | V34: - | W34: 252.57 | X34: a | Y34: 268.01
A35: 45665 | B35: 25 | D35: ENEBRAS | E35: 3671_GRAAC - 3671-24 - GRAAC - 1° E 7° ANDAR | G35: Michel | H35: Bruna | I35: 17023.2 | K35: 264 | L35: FECHADO | M35: Aguardando aprovação | N35: - | O35: - | P35: - | Q35: - | R35: -
A36: 45664 | B36: 26 | D36: UNION RHAC | E36: NISSIN CHOCOLATE | G36: Emanuel | H36: Vinicius | I36: 76571.13 | K36: 888 | L36: FECHADO | M36: - | N36: - | O36: - | P36: - | Q36: - | R36: -
A37: 45665 | B37: 27 | D37: ADALTA ENGENHARIA | E37: COPERMED - POUSO ALGRE - MG | G37: Fernando | H37: Joao | I37: 70206.27 | K37: 840 | L37: FECHADO | M37: - | N37: - | O37: - | P37: - | Q37: - | R37: -
A38: 45665 | B38: 28 | D38: K SET | E38: - | G38: Gabriel | H38: Bruna | I38: 1595.63 | K38: 24 | L38: FECHADO | M38: - | N38: - | O38: - | P38: - | Q38: - | R38: -
A39: 45665 | B39: 29 | D39: COLDTERMICA | E39: RNR - FLAMBOYANT - GO | G39: Gabriel | H39: Gabriella | I39: 6177.05 | K39: 48 | L39: CANCELADO | M39: - | N39: - | O39: - | P39: - | Q39: - | R39: -
A40: 45665 | B40: 30 | D40: R1 SOLUCOES | E40: - | G40: Gabriel | H40: Janaina | I40: 3975.32 | K40: 48 | L40: CANCELADO | M40: Negociando | N40: - | O40: - | P40: - | Q40: - | R40: -
A41: 45665 | B41: 31 | D41: GF ENGENHARIA | E41: - | G41: Gabriel | H41: Ricardo | I41: 728.5 | K41: - | L41: CANCELADO | M41: - | N41: - | O41: - | P41: - | Q41: - | R41: -
A42: 45665 | B42: 32 | D42: NEWSET | E42: HOSPITAL SABARA | G42: Aldavir | H42: Rodrigo | I42: 1207781.3 | K42: 15144 | L42: CANCELADO | M42: FECHADO PELA ARPOL | N42: - | O42: - | P42: - | Q42: - | R42: -
A43: 45665 | B43: 33 | D43: NEWSET | E43: HOSPITAL SÃO LUIZ - OSASCO | G43: Aldavir | H43: Felipe | I43: 48379.54 | K43: 528 | L43: CANCELADO | M43: - | N43: - | O43: - | P43: - | Q43: - | R43: -
A44: 45665 | B44: 34 | D44: AIR GREEN | E44: - | G44: Fernando | H44: Renata | I44: 3110.21 | K44: 48 | L44: FECHADO | M44: - | N44: - | O44: - | P44: - | Q44: - | R44: -
A45: 45665 | B45: 35 | D45: CARLOS ANTONIO | E45: LABORATÓRIO QUÍMICO FARMACÊUTICO DA AERONÁUTICA - LAQFA | G45: Emanuel | H45: Carlos | I45: 61538.58 | K45: 672 | L45: CANCELADO | M45: Em vias de fechar, mas cliente final está tentando compraar pelo Rio | N45: - | O45: - | P45: - | Q45: CAMALEAO ENGENHARIA | R45: N/E
A46: 45665 | B46: 36 | D46: ECOLOGIC AIR | E46: ATACADAO - PALMAS III - TO | G46: Michel | H46: Genilson | I46: 257079.26 | K46: 2592 | L46: CANCELADO | M46: - | N46: - | O46: - | P46: - | Q46: PLANENRAC | R46: N/E
A47: 45665 | B47: 37 | D47: ECOLOGIC AIR | E47: ATACADAO - LOJA OSASCO PANORAMICA II - SP | G47: Michel | H47: Genilson | I47: 238482.66 | K47: 2402.4 | L47: CANCELADO | M47: - | N47: - | O47: - | P47: - | Q47: PLANENRAC | R47: N/E
A48: 45665 | B48: 38 | D48: ECOLOGIC AIR | E48: ATACADAO - REDENCAO - PA | G48: Michel | H48: Genilson | I48: 170730.37 | K48: 1729.2 | L48: CANCELADO | M48: - | N48: - | O48: - | P48: - | Q48: PLANENRAC | R48: N/E
A49: 45665 | B49: 39 | D49: ENGEMAC | E49: HOSPITAL UNIMED - BLOCO 2 - SÃO CARLOS - SP | G49: Fernando | H49: Rodrigo | I49: 170134.38 | K49: 1944 | L49: CANCELADO | M49: PREVISAO ABRIL | N49: - | O49: - | P49: - | Q49: GRAU ENGENHARIA | R49: N/E
A50: 45665 | B50: 40 | D50: BOM CLIMA | E50: - | G50: Gabriel | H50: Roberto | I50: 9206.41 | K50: 120 | L50: FECHADO | M50: - | N50: - | O50: - | P50: - | Q50: - | R50: -
A51: 45665 | B51: 41 | D51: HARCO ENGENHARIA | E51: - | G51: Emanuel | H51: Andre | I51: 9333.29 | K51: 120 | L51: CANCELADO | M51: - | N51: - | O51: - | P51: - | Q51: - | R51: -
A52: 45665 | B52: 42 | D52: AR SISTEMAS | E52: - | G52: Michel | H52: Thatila | I52: 3936.47 | K52: 48 | L52: FECHADO | M52: - | N52: - | O52: - | P52: - | Q52: - | R52: -
A53: 45666 | B53: 43 | D53: MASSER REFRIGERACAO | E53: - | G53: Gabriel | H53: Joao | I53: 1789.27 | K53: - | L53: CANCELADO | M53: Proposta reenviada | N53: - | O53: - | P53: - | Q53: - | R53: -
A54: 45666 | B54: 44 | D54: CLIMAPALA | E54: GRANDVISION - SHOPPING PAULISTA | G54: Michel | H54: Marcio | I54: 13466.98 | K54: 144 | L54: CANCELADO | M54: FEITO EM CHAPA | N54: - | O54: - | P54: - | Q54: MARQUI SOLUCOES E PROJETOS | R54: N/E
A55: 45666 | B55: 45 | D55: GENILSON GERALDO | E55: ATACADAO - LAURO DE FREITAS - BA | G55: Michel | H55: Genilson | I55: 177912.42 | K55: 1760.4 | L55: CANCELADO | M55: - | N55: - | O55: - | P55: - | Q55: ARCO + | R55: N/E
A56: 45667 | B56: 46 | D56: SCS ENGENHARIA | E56: - | G56: Gabriel | H56: Christopher | I56: 4417.5 | K56: - | L56: FECHADO | M56: - | N56: - | O56: - | P56: - | Q56: - | R56: -
A57: 45667 | B57: 47 | D57: ENGEMAC | E57: LEGIAO DA BOA VONTADE - BOM RETIRO - SP | G57: Fernando | H57: Edmilson | I57: 4198.02 | K57: 48 | L57: CANCELADO | M57: - | N57: - | O57: - | P57: - | Q57: ENGEMAC | R57: ALUPIR
A58: 45667 | B58: 48 | D58: QUALITY AIR | E58: WHITE & CASE - FARIA LIMA - SP | G58: Michel | H58: Rodrigo | I58: 52358.28 | K58: 456 | L58: CANCELADO | M58: - | N58: - | O58: - | P58: - | Q58: - | R58: -
A59: 45667 | B59: 49 | D59: AWA AR CONDICIONADO | E59: MIX - BOA VIAGEM - PE | G59: Guilherme | H59: Marcela | I59: 8086.95 | K59: 144 | L59: FECHADO | M59: - | N59: - | O59: - | P59: - | Q59: - | R59: -
A60: 45667 | B60: 50 | D60: GENILSON GERALDO | E60: CBS SIDER SHOPPING - VOLTA REDONDA - RJ | G60: Gabriel | H60: Genilson | I60: 88793.64 | K60: 840 | L60: CANCELADO | M60: - | N60: - | O60: - | P60: - | Q60: - | R60: -
A61: 45667 | B61: 51 | D61: TEKNOAR | E61: HOSPITAL BENEFICIENTE - DONA ELMIRIA SILVEIRO BARBOSA | G61: Gabriel | H61: Mario | I61: 34000 | K61: 576 | L61: FECHADO | M61: - | N61: - | O61: - | P61: - | Q61: - | R61: -
A62: 45667 | B62: 52 | D62: RDS ENGENHARIA | E62: MAXI SHOPPING | G62: Aldavir | H62: Clevison | I62: 123973.35 | L62: CANCELADO
A63: 45667 | B63: 53 | D63: RDS ENGENHARIA | E63: SUPERMERCADO TAUSTE | G63: Aldavir | H63: Clevison | I63: 154829.39 | L63: CANCELADO
A64: 45667 | B64: 54 | D64: GLOBAL AR CONDICIONADO | E64: PROMEDON - SOROCABA - SP | G64: Emanuel | H64: Claudemir | I64: 73497.59 | K64: 672 | L64: CANCELADO | M64: OBRA INOVACAO AR | N64: - | O64: - | P64: - | Q64: - | R64: -
A65: 45667 | B65: 55 | D65: ECOTHERM | E65: HOSPITAL DE FRANCA | G65: Emanuel | H65: Selma | I65: 275605.01 | K65: 3600 | L65: CANCELADO | M65: Aberto, estou marcando no cliente para proxima semana | N65: - | O65: - | P65: - | Q65: - | R65: -
A66: 45667 | B66: 56 | D66: RM3 ENGENHARIA | E66: MERCADÃO ATACADISTA ENSEADA - GUARUJA - SP | G66: Guilherme | H66: Diego | I66: 124316.04 | K66: 1200 | L66: FECHADO | M66: SERA FECHADO ATRAVES DO NEWTON | N66: - | O66: - | P66: - | Q66: RM3 ENGENHARIA | R66: MPU
A67: 45670 | B67: 57 | D67: TARKAT REFRIGERACAO | E67: - | G67: Michel | H67: Artur | I67: 5091.99 | K67: - | L67: FECHADO | M67: - | N67: - | O67: - | P67: - | Q67: - | R67: -
A68: 45670 | B68: 58 | D68: BOM CLIMA | E68: - | G68: Gabriel | H68: Roberto | I68: 17563.67 | K68: 240 | L68: CANCELADO | M68: - | N68: - | O68: - | P68: - | Q68: - | R68: -
A69: 45670 | B69: 59 | D69: EBM ENGENHARIA | E69: BANDEIRAS CENTRO EMPRESARIAL - PROTESTANTES -VOTORANTIM | G69: Emanuel | H69: Laelda | I69: 22219.21 | K69: 77.6 | L69: CANCELADO | M69: - | N69: - | O69: - | P69: - | Q69: MAC ENGENHARIA E CLIMATIZACAO | R69: MPU
A70: 45670 | B70: 60 | D70: WELLNESS | E70: - | G70: Gabriel | H70: Ivanise | I70: 33405.5 | K70: 360 | L70: FECHADO | M70: - | N70: - | O70: - | P70: - | Q70: - | R70: -
A71: 45670 | B71: 61 | D71: FIDELISAR | E71: HAPVIDA - CLINICA SOROCABA - SP | G71: Gabriel | H71: Edson | I71: 37894.17 | K71: 408 | L71: CANCELADO | M71: - | N71: - | O71: - | P71: - | Q71: - | R71: -
A72: 45670 | B72: 62 | D72: RM3 ENGENHARIA | E72: NIKE UNITE - SANTA MARIA OUTLET | G72: Guilherme | H72: Lenah | I72: 104137.26 | K72: 1032 | L72: CANCELADO | M72: CLIENTE PERDEU A OBRA | N72: - | O72: - | P72: - | Q72: - | R72: MPU
A73: 45670 | B73: 63 | D73: AWA AR CONDICIONADO | E73: D'FAMY EMPREENDIMENTOS - OSASCO - SÃO PAULO - SP | G73: Guilherme | H73: Maria Julia | I73: 73128 | K73: 696 | L73: CANCELADO | M73: CLIENTE PERDEU A OBRA | N73: - | O73: - | P73: - | Q73: - | R73: -
A74: 45670 | B74: 64 | D74: COLDTERMICA | E74: RNR - SHOP MORUMBI - SP | G74: Gabriel | H74: Gabriella | I74: 166827.46 | K74: 1560 | L74: CANCELADO | M74: - | N74: - | O74: - | P74: - | Q74: - | R74: -
A75: 45670 | B75: 65 | D75: AMS INSTALACOES | E75: ATACADAO - LAURO DE FREITAS - BA | G75: Gabriel | H75: Albertino | I75: 177912.42 | K75: 1760.4 | L75: CANCELADO | M75: - | N75: - | O75: - | P75: - | Q75: PLANENRAC | R75: N/E
A76: 45670 | B76: 66 | D76: VOAR AVIATION | E76: - | G76: Gabriel | H76: Roniel | I76: 4126.31 | K76: 24 | L76: CANCELADO | M76: - | N76: - | O76: - | P76: - | Q76: - | R76: -
A77: 45670 | B77: 67 | D77: LEONE ENGENHARIA | E77: ORFEU CAFÉ - FAZENDA SERTÃOZINHO - BOTELHOS - MG | G77: Gabriel | H77: Adriano | I77: 69294.29 | K77: 672 | L77: CANCELADO | M77: - | N77: - | O77: - | P77: - | Q77: LC ARQUITETURA E ENGENHARIA | R77: MPU
A78: 45670 | B78: 68 | D78: INOVECTOR | E78: BARTIRA - REQ 2.04 | G78: Fernando | H78: Cristina | I78: 2907.6 | K78: - | L78: FECHADO | M78: - | N78: - | O78: - | P78: - | Q78: - | R78: -
A79: 45671 | B79: 69 | D79: ENGEMAC | E79: UNIMED JAÚ - AMPLIAÇÃO UTI | G79: Fernando | H79: Sandro | I79: 17943.01 | K79: 240 | L79: FECHADO | M79: - | N79: - | O79: - | P79: - | Q79: - | R79: -
A80: 45671 | B80: 70 | D80: ADRIATIC | E80: C&A - SHOPPING VALINHOS - SP | G80: Emanuel | H80: Carlos | I80: 107779.99 | K80: 1320 | L80: FECHADO | M80: - | N80: - | O80: - | P80: - | Q80: SISTEMAS ENGENHARIA | R80: MPU
A81: 45671 | B81: 71 | D81: CONFORTO ENGENHARIA | E81: HOSPITAL MUNICIPAL - DOUTOR FERNANDO MAURO PIRES DA ROCHA - VILA MARACANA | G81: Michel | H81: Pedro | I81: 34696.35 | K81: 360 | L81: CANCELADO | M81: - | N81: - | O81: - | P81: - | Q81: - | R81: -
A82: 45671 | B82: 72 | D82: COLD CONTROL | E82: WHITE & CASE - FARIA LIMA - SP | G82: Emanuel | H82: Guilherme | I82: 52358.28 | K82: 456 | L82: CANCELADO | M82: - | N82: - | O82: - | P82: - | Q82: - | R82: -
A83: 45671 | B83: 73 | D83: AIR SUPPLY | E83: SUPERMERCADOS PIERIM - LOJA 07 - SÃO JOSE DO RIO PARDO | G83: Gabriel | H83: Pedro | I83: 58484.3 | K83: 600 | L83: CANCELADO | M83: - | N83: - | O83: - | P83: - | Q83: TERMOCLIMA ENGENHARIA | R83: ACO GALVANIZADO
A84: 45671 | B84: 74 | D84: AR SISTEMAS | E84: - | G84: Michel | H84: Thatila | I84: 4256 | K84: - | L84: FECHADO | M84: - | N84: - | O84: - | P84: - | Q84: - | R84: -
A85: 45671 | B85: 75 | D85: FL HVAC | E85: SMART FIT - BUCAREIN - JOINVILLE - SC | G85: Guilherme | H85: Ynnaie | I85: 52518.88 | K85: 576 | L85: CANCELADO | M85: CLIENTE PERDEU A OBRA | N85: - | O85: - | P85: - | Q85: CONTRAT AR | R85: MPU
A86: 45671 | B86: 76 | D86: FL HVAC | E86: SMART FIT - SÃO MIGUEL PAULISTA 3 - SP | G86: Guilherme | H86: Ynnaie | I86: 101845.23 | K86: 1032 | L86: CANCELADO | M86: CLIENTE PERDEU A OBRA | N86: - | O86: - | P86: - | Q86: CONTRAT AR | R86: MPU
A87: 45671 | B87: 77 | D87: AIR NET | E87: Santa Casa - RM13 | G87: Fernando | H87: Ricardo | I87: 16883.54 | K87: 168 | L87: PERDIDO | M87: - | N87: ARCOTEC | O87: PREÇO | P87: - | Q87: - | R87: -
A88: 45671 | B88: 78 | D88: AR SISTEMAS | E88: - | G88: Michel | H88: Thatila | I88: 9663.01 | K88: - | L88: FECHADO | M88: - | N88: - | O88: - | Q88: - | R88: -
A89: 45671 | B89: 79 | D89: FL HVAC | E89: SMART FIT - SÃO GONCALO BARCELOS - VISTA ALEGE - RJ | G89: Guilherme | H89: Ynnaie | I89: 52586.08 | K89: 528 | L89: CANCELADO | M89: CLIENTE PERDEU A OBRA | N89: - | O89: - | P89: - | Q89: CONTRAT AR | R89: MPU
A90: 45672 | B90: 80 | D90: HVAC ENGENHARIA | E90: - | G90: Michel | H90: Alvaro | I90: 303.31 | K90: - | L90: CANCELADO | M90: - | N90: - | O90: - | P90: - | Q90: - | R90: -
A91: 45672 | B91: 81 | D91: THERMOMATIC | E91: - | G91: Gabriel | H91: Calil | I91: 2079.57 | K91: - | L91: FECHADO | M91: - | N91: - | O91: - | P91: - | Q91: - | R91: - | S91: -
A92: 45672 | B92: 82 | D92: SCS ENGENHARIA | E92: - | G92: Gabriel | H92: Christopher | I92: 4305.85 | K92: 24 | L92: FECHADO | M92: - | N92: - | O92: - | P92: - | Q92: - | R92: -
A93: 45672 | B93: 83 | D93: KONAR | E93: 422-24 - JHSF -Usina - Adt | G93: Michel | H93: Fabio | I93: 25170.68 | K93: 216 | L93: PERDIDO | M93: PACOTE | N93: ARCOTEC | O93: PACOTE | P93: - | Q93: - | R93: -
A94: 45673 | B94: 84 | D94: AMS INSTALACOES | E94: NOVA SEDE - SICOOB AGROCREDI - GUAXUPE - MG | G94: Gabriel | H94: Albertino | I94: 194099.96 | K94: 1824 | L94: CANCELADO | M94: - | N94: - | O94: - | P94: -
A95: 45674 | B95: 85 | D95: PU DUTOS | E95: DM SERVICOS EM GERAL - AREA DE MOAGEM | G95: Gabriel | H95: Thiago | I95: 23984.88 | K95: 288 | L95: CANCELADO | M95: - | N95: - | O95: - | P95: - | Q95: - | R95: -
A96: 45674 | B96: 86 | D96: AIR TIME | E96: CAISM - CENTRO DE ATENÇÃO INTEGRADA A SAÚDE DA MULHER - JUNDIAI - SP | G96: Emanuel | H96: Renan | I96: 65374.74 | K96: 768 | L96: FECHADO | M96: - | N96: - | O96: - | P96: - | Q96: - | R96: -
A97: 45677 | B97: 87 | D97: MONTES CLIMA | E97: - | G97: Gabriel | H97: Roberto | I97: 2442.72 | K97: 24 | L97: FECHADO | M97: - | N97: - | O97: - | P97: - | Q97: - | R97: -
A98: 45673 | B98: 88 | D98: BRISA AR CONDICIONADO | E98: VALGROUP LTDA - LORENA - SP | G98: Michel | H98: Sidnei | I98: 230102.64 | K98: 1968 | L98: CANCELADO | M98: - | N98: - | O98: - | P98: - | Q98: BBT CLIMATIZACAO | R98: N/E
A99: 45673 | B99: 89 | D99: AIR GREEN | E99: - | G99: Fernando | H99: Renata | I99: 11342.42 | K99: 144 | L99: FECHADO | M99: - | N99: - | P99: - | Q99: - | R99: -
A100: 45674 | B100: 90 | D100: NEW AIR | E100: - | G100: Fernando | H100: Igor | I100: 9682.07 | K100: 120 | L100: FECHADO | M100: - | N100: - | O100: - | P100: - | Q100: - | R100: -
A101: 45673 | B101: 91 | D101: HITECH INSTALACOES | E101: STUDIO VILA ANDRADE - SP | G101: Gabriel | H101: Edmundo | I101: 18830.19 | K101: 192 | L101: CANCELADO | M101: - | N101: - | O101: - | P101: - | Q101: - | R101: -
A102: 45674 | B102: 92 | D102: THERMOMATIC | E102: - | G102: Gabriel | H102: Michel | I102: 4328.8 | K102: - | L102: FECHADO | M102: - | N102: - | O102: - | P102: - | Q102: - | R102: -
A103: 45674 | B103: 93 | D103: AWA AR CONDICIONADO | E103: ATACADAO - BANGU SHOPPING - RJ | G103: Guilherme | H103: Maria Julia | I103: 125238.88 | K103: 1176 | L103: CANCELADO | M103: - | N103: - | O103: - | P103: - | Q103: ARCO + | R103: N/E
A104: 45674 | B104: 94 | D104: AIRPLAN | E104: RENNER SHOPPING MORUMBI - SÃO PAULO - SP | G104: Gabriel | H104: Laercio | I104: 205337.59 | K104: 1848 | L104: CANCELADO | M104: - | N104: - | O104: - | P104: - | Q104: SISTEMAS ENGENHARIA | R104: MPU
A105: 45674 | B105: 95 | D105: LKT AR CONDICIONADO | E105: WHITE & CASE | G105: Fernando | H105: Rafael | I105: 46570.57 | K105: 456 | L105: CANCELADO | M105: BOAS CHANCES | N105: - | O105: - | P105: - | Q105: - | R105: -
A106: 45674 | B106: 96 | D106: K SET | E106: - | G106: Gabriel | H106: Bruna | I106: 1707.65 | K106: 24 | L106: FECHADO | M106: - | N106: - | O106: - | P106: - | Q106: - | R106: -
A107: 45674 | B107: 97 | D107: COLD SERVICE | E107: - | G107: Gabriel | H107: Rogerio | I107: 1242.8 | K107: 7.2 | L107: CANCELADO | M107: - | N107: - | O107: - | P107: - | Q107: - | R107: -
A108: 45674 | B108: 98 | D108: AMS INSTALACOES | E108: ATACADAO - BANGU SHOPPING - RJ | G108: Gabriel | H108: Albertino | I108: 103725.05 | K108: 1200 | L108: FECHADO | M108: - | N108: - | O108: - | P108: - | Q108: ARCO + | R108: N/E
...

Sheet FOLLOW-UP
A1: =TODAY() -> 46176 | B1: RESUMO DOS ORÇAMENTOS - ALU-PIR
A2: Data | B2: Número | C2: Revisão | D2: Cliente | E2: Obra | F2: Vendedor | G2: Contato | H2: Valor | I2: Comissão | J2: STATUS | K2: ATUALIZAÇÃO | L2: ESPECIFICAÇÃO
A3: =IF(ORCAMENTOS!A11="","",ORCAMENTOS!A11) -> 45660 | B3: =IF(ORCAMENTOS!B11="","",ORCAMENTOS!B11) -> 1 | C3: =IF(ORCAMENTOS!C11="","",ORCAMENTOS!C11) | D3: =IF(ORCAMENTOS!D11="","",ORCAMENTOS!D11) -> KEEVA TEIC | E3: =IF(ORCAMENTOS!E11="","",ORCAMENTOS!E11) -> - | F3: =IF(ORCAMENTOS!G11="","",ORCAMENTOS!G11) -> Michel | G3: =IF(ORCAMENTOS!H11="","",ORCAMENTOS!H11) -> Rachel | H3: =IF(ORCAMENTOS!I11="","",ORCAMENTOS!I11) -> 3411.11 | I3: =IF(ORCAMENTOS!J11="","",ORCAMENTOS!J11) | J3: =IF(ORCAMENTOS!L11="","",ORCAMENTOS!L11) -> FECHADO | K3: =IF(ORCAMENTOS!M11="","",ORCAMENTOS!M11) | L3: =IF(ORCAMENTOS!R11="","",ORCAMENTOS!R11) -> -
A4: =IF(ORCAMENTOS!A12="","",ORCAMENTOS!A12) -> 45663 | B4: =IF(ORCAMENTOS!B12="","",ORCAMENTOS!B12) -> 2 | C4: =IF(ORCAMENTOS!C12="","",ORCAMENTOS!C12) | D4: =IF(ORCAMENTOS!D12="","",ORCAMENTOS!D12) -> SOLAR AR | E4: =IF(ORCAMENTOS!E12="","",ORCAMENTOS!E12) -> HOSPITAL DE REGISTRO - SIRIO LIBANES - DUTOS CENTRO CIRURGICO | F4: =IF(ORCAMENTOS!G12="","",ORCAMENTOS!G12) -> Michel | G4: =IF(ORCAMENTOS!H12="","",ORCAMENTOS!H12) -> Claudenir | H4: =IF(ORCAMENTOS!I12="","",ORCAMENTOS!I12) -> 8092.7 | I4: =IF(ORCAMENTOS!J12="","",ORCAMENTOS!J12) | J4: =IF(ORCAMENTOS!L12="","",ORCAMENTOS!L12) -> FECHADO | K4: =IF(ORCAMENTOS!M12="","",ORCAMENTOS!M12) | L4: =IF(ORCAMENTOS!R12="","",ORCAMENTOS!R12) -> -
A5: =IF(ORCAMENTOS!A13="","",ORCAMENTOS!A13) -> 45663 | B5: =IF(ORCAMENTOS!B13="","",ORCAMENTOS!B13) -> 3 | C5: =IF(ORCAMENTOS!C13="","",ORCAMENTOS!C13) | D5: =IF(ORCAMENTOS!D13="","",ORCAMENTOS!D13) -> INOVECTOR | E5: =IF(ORCAMENTOS!E13="","",ORCAMENTOS!E13) -> HOSP. MORUMBI_SADT | F5: =IF(ORCAMENTOS!G13="","",ORCAMENTOS!G13) -> Fernando | G5: =IF(ORCAMENTOS!H13="","",ORCAMENTOS!H13) -> Eliete | H5: =IF(ORCAMENTOS!I13="","",ORCAMENTOS!I13) -> 14294.94 | I5: =IF(ORCAMENTOS!J13="","",ORCAMENTOS!J13) | J5: =IF(ORCAMENTOS!L13="","",ORCAMENTOS!L13) -> FECHADO | K5: =IF(ORCAMENTOS!M13="","",ORCAMENTOS!M13) | L5: =IF(ORCAMENTOS!R13="","",ORCAMENTOS!R13) -> -
A6: =IF(ORCAMENTOS!A14="","",ORCAMENTOS!A14) -> 45663 | B6: =IF(ORCAMENTOS!B14="","",ORCAMENTOS!B14) -> 4 | C6: =IF(ORCAMENTOS!C14="","",ORCAMENTOS!C14) | D6: =IF(ORCAMENTOS!D14="","",ORCAMENTOS!D14) -> REWELL OTAVIO | E6: =IF(ORCAMENTOS!E14="","",ORCAMENTOS!E14) -> ENG BRUNO NY TOWER | F6: =IF(ORCAMENTOS!G14="","",ORCAMENTOS!G14) -> Gabriel | G6: =IF(ORCAMENTOS!H14="","",ORCAMENTOS!H14) -> Rewell | H6: =IF(ORCAMENTOS!I14="","",ORCAMENTOS!I14) -> 2259.26 | I6: =IF(ORCAMENTOS!J14="","",ORCAMENTOS!J14) | J6: =IF(ORCAMENTOS!L14="","",ORCAMENTOS!L14) -> CANCELADO | K6: =IF(ORCAMENTOS!M14="","",ORCAMENTOS!M14) | L6: =IF(ORCAMENTOS!R14="","",ORCAMENTOS!R14) -> -
A7: =IF(ORCAMENTOS!A15="","",ORCAMENTOS!A15) -> 45663 | B7: =IF(ORCAMENTOS!B15="","",ORCAMENTOS!B15) -> 5 | C7: =IF(ORCAMENTOS!C15="","",ORCAMENTOS!C15) | D7: =IF(ORCAMENTOS!D15="","",ORCAMENTOS!D15) -> INOVECTOR | E7: =IF(ORCAMENTOS!E15="","",ORCAMENTOS!E15) -> VILLA LOBOS - REQ 2.04 | F7: =IF(ORCAMENTOS!G15="","",ORCAMENTOS!G15) -> Fernando | G7: =IF(ORCAMENTOS!H15="","",ORCAMENTOS!H15) -> Cristina | H7: =IF(ORCAMENTOS!I15="","",ORCAMENTOS!I15) -> 6933.2 | I7: =IF(ORCAMENTOS!J15="","",ORCAMENTOS!J15) | J7: =IF(ORCAMENTOS!L15="","",ORCAMENTOS!L15) -> FECHADO | K7: =IF(ORCAMENTOS!M15="","",ORCAMENTOS!M15) | L7: =IF(ORCAMENTOS!R15="","",ORCAMENTOS!R15) -> -
A8: =IF(ORCAMENTOS!A16="","",ORCAMENTOS!A16) -> 45663 | B8: =IF(ORCAMENTOS!B16="","",ORCAMENTOS!B16) -> 6 | C8: =IF(ORCAMENTOS!C16="","",ORCAMENTOS!C16) | D8: =IF(ORCAMENTOS!D16="","",ORCAMENTOS!D16) -> REWELL OTAVIO | E8: =IF(ORCAMENTOS!E16="","",ORCAMENTOS!E16) -> RESIDENCIA UNIFAMILIAR - FERNANDO PORTOLANI DE ANDRADE | F8: =IF(ORCAMENTOS!G16="","",ORCAMENTOS!G16) -> Gabriel | G8: =IF(ORCAMENTOS!H16="","",ORCAMENTOS!H16) -> Rewell | H8: =IF(ORCAMENTOS!I16="","",ORCAMENTOS!I16) -> 9106.66 | I8: =IF(ORCAMENTOS!J16="","",ORCAMENTOS!J16) | J8: =IF(ORCAMENTOS!L16="","",ORCAMENTOS!L16) -> CANCELADO | K8: =IF(ORCAMENTOS!M16="","",ORCAMENTOS!M16) | L8: =IF(ORCAMENTOS!R16="","",ORCAMENTOS!R16) -> CHAPA DE ACO GALVANIZADO
A9: =IF(ORCAMENTOS!A17="","",ORCAMENTOS!A17) -> 45663 | B9: =IF(ORCAMENTOS!B17="","",ORCAMENTOS!B17) -> 7 | C9: =IF(ORCAMENTOS!C17="","",ORCAMENTOS!C17) | D9: =IF(ORCAMENTOS!D17="","",ORCAMENTOS!D17) -> REWELL OTAVIO | E9: =IF(ORCAMENTOS!E17="","",ORCAMENTOS!E17) -> SALA 104 - NY TOWER - ARACATUBA - SP | F9: =IF(ORCAMENTOS!G17="","",ORCAMENTOS!G17) -> Gabriel | G9: =IF(ORCAMENTOS!H17="","",ORCAMENTOS!H17) -> Rewell | H9: =IF(ORCAMENTOS!I17="","",ORCAMENTOS!I17) -> 26029.3 | I9: =IF(ORCAMENTOS!J17="","",ORCAMENTOS!J17) | J9: =IF(ORCAMENTOS!L17="","",ORCAMENTOS!L17) -> CANCELADO | K9: =IF(ORCAMENTOS!M17="","",ORCAMENTOS!M17) | L9: =IF(ORCAMENTOS!R17="","",ORCAMENTOS!R17) -> CHAPA DE ACO GALVANIZADO
A10: =IF(ORCAMENTOS!A18="","",ORCAMENTOS!A18) -> 45663 | B10: =IF(ORCAMENTOS!B18="","",ORCAMENTOS!B18) -> 8 | C10: =IF(ORCAMENTOS!C18="","",ORCAMENTOS!C18) | D10: =IF(ORCAMENTOS!D18="","",ORCAMENTOS!D18) -> GRUPO R1 | E10: =IF(ORCAMENTOS!E18="","",ORCAMENTOS!E18) -> - | F10: =IF(ORCAMENTOS!G18="","",ORCAMENTOS!G18) -> Gabriel | G10: =IF(ORCAMENTOS!H18="","",ORCAMENTOS!H18) -> Janaina | H10: =IF(ORCAMENTOS!I18="","",ORCAMENTOS!I18) -> 3232.69 | I10: =IF(ORCAMENTOS!J18="","",ORCAMENTOS!J18) | J10: =IF(ORCAMENTOS!L18="","",ORCAMENTOS!L18) -> CANCELADO | K10: =IF(ORCAMENTOS!M18="","",ORCAMENTOS!M18) -> Negociando | L10: =IF(ORCAMENTOS!R18="","",ORCAMENTOS!R18) -> -
A11: =IF(ORCAMENTOS!A19="","",ORCAMENTOS!A19) -> 45663 | B11: =IF(ORCAMENTOS!B19="","",ORCAMENTOS!B19) -> 9 | C11: =IF(ORCAMENTOS!C19="","",ORCAMENTOS!C19) | D11: =IF(ORCAMENTOS!D19="","",ORCAMENTOS!D19) -> AWA AR CONDICIONADO | E11: =IF(ORCAMENTOS!E19="","",ORCAMENTOS!E19) -> ATACADAO - LAURO DE FREITAS CAJI - BA | F11: =IF(ORCAMENTOS!G19="","",ORCAMENTOS!G19) -> Guilherme | G11: =IF(ORCAMENTOS!H19="","",ORCAMENTOS!H19) -> Maria Julia | H11: =IF(ORCAMENTOS!I19="","",ORCAMENTOS!I19) -> 175342.6 | I11: =IF(ORCAMENTOS!J19="","",ORCAMENTOS!J19) | J11: =IF(ORCAMENTOS!L19="","",ORCAMENTOS!L19) -> CANCELADO | K11: =IF(ORCAMENTOS!M19="","",ORCAMENTOS!M19) | L11: =IF(ORCAMENTOS!R19="","",ORCAMENTOS!R19) -> N/E
A12: =IF(ORCAMENTOS!A20="","",ORCAMENTOS!A20) -> 45663 | B12: =IF(ORCAMENTOS!B20="","",ORCAMENTOS!B20) -> 10 | C12: =IF(ORCAMENTOS!C20="","",ORCAMENTOS!C20) | D12: =IF(ORCAMENTOS!D20="","",ORCAMENTOS!D20) -> CONSTARCO | E12: =IF(ORCAMENTOS!E20="","",ORCAMENTOS!E20) -> - | F12: =IF(ORCAMENTOS!G20="","",ORCAMENTOS!G20) -> Fernando | G12: =IF(ORCAMENTOS!H20="","",ORCAMENTOS!H20) -> Fabricio | H12: =IF(ORCAMENTOS!I20="","",ORCAMENTOS!I20) -> 297411.92 | I12: =IF(ORCAMENTOS!J20="","",ORCAMENTOS!J20) | J12: =IF(ORCAMENTOS!L20="","",ORCAMENTOS!L20) -> CANCELADO | K12: =IF(ORCAMENTOS!M20="","",ORCAMENTOS!M20) -> PERDERAM A OBRA | L12: =IF(ORCAMENTOS!R20="","",ORCAMENTOS!R20) -> -
A13: =IF(ORCAMENTOS!A21="","",ORCAMENTOS!A21) -> 45663 | B13: =IF(ORCAMENTOS!B21="","",ORCAMENTOS!B21) -> 11 | C13: =IF(ORCAMENTOS!C21="","",ORCAMENTOS!C21) | D13: =IF(ORCAMENTOS!D21="","",ORCAMENTOS!D21) -> INOVECTOR | E13: =IF(ORCAMENTOS!E21="","",ORCAMENTOS!E21) -> ANALIA FRANCO - REQ 2.03 | F13: =IF(ORCAMENTOS!G21="","",ORCAMENTOS!G21) -> Fernando | G13: =IF(ORCAMENTOS!H21="","",ORCAMENTOS!H21) -> Eliete | H13: =IF(ORCAMENTOS!I21="","",ORCAMENTOS!I21) -> 9352.59 | I13: =IF(ORCAMENTOS!J21="","",ORCAMENTOS!J21) | J13: =IF(ORCAMENTOS!L21="","",ORCAMENTOS!L21) -> FECHADO | K13: =IF(ORCAMENTOS!M21="","",ORCAMENTOS!M21) | L13: =IF(ORCAMENTOS!R21="","",ORCAMENTOS!R21) -> -
A14: =IF(ORCAMENTOS!A22="","",ORCAMENTOS!A22) -> 45663 | B14: =IF(ORCAMENTOS!B22="","",ORCAMENTOS!B22) -> 12 | C14: =IF(ORCAMENTOS!C22="","",ORCAMENTOS!C22) | D14: =IF(ORCAMENTOS!D22="","",ORCAMENTOS!D22) -> INOVECTOR | E14: =IF(ORCAMENTOS!E22="","",ORCAMENTOS!E22) -> HOSP.OSASCO - REQ 2.04 | F14: =IF(ORCAMENTOS!G22="","",ORCAMENTOS!G22) -> Fernando | G14: =IF(ORCAMENTOS!H22="","",ORCAMENTOS!H22) -> Cristina | H14: =IF(ORCAMENTOS!I22="","",ORCAMENTOS!I22) -> 169.83 | I14: =IF(ORCAMENTOS!J22="","",ORCAMENTOS!J22) | J14: =IF(ORCAMENTOS!L22="","",ORCAMENTOS!L22) -> CANCELADO | K14: =IF(ORCAMENTOS!M22="","",ORCAMENTOS!M22) | L14: =IF(ORCAMENTOS!R22="","",ORCAMENTOS!R22) -> -
... A3186: =IF(ORCAMENTOS!A3194="","",ORCAMENTOS!A3194) | B3186: =IF(ORCAMENTOS!B3194="","",ORCAMENTOS!B3194) | C3186: =IF(ORCAMENTOS!C3194="","",ORCAMENTOS!C3194) | D3186: =IF(ORCAMENTOS!D3194="","",ORCAMENTOS!D3194) | E3186: =IF(ORCAMENTOS!E3194="","",ORCAMENTOS!E3194) | F3186: =IF(ORCAMENTOS!G3194="","",ORCAMENTOS!G3194) | G3186: =IF(ORCAMENTOS!H3194="","",ORCAMENTOS!H3194) | H3186: =IF(ORCAMENTOS!I3194="","",ORCAMENTOS!I3194) | I3186: =IF(ORCAMENTOS!J3194="","",ORCAMENTOS!J3194) | J3186: =IF(ORCAMENTOS!L3194="","",ORCAMENTOS!L3194) | K3186: =IF(ORCAMENTOS!M3194="","",ORCAMENTOS!M3194) | L3186: =IF(ORCAMENTOS!R3194="","",ORCAMENTOS!R3194)
D3188: =SUBTOTAL(9,H3:H3186) -> 171059.67 | L3188: =IF(ORCAMENTOS!R704="","",ORCAMENTOS!R704) -> -
L3189: =IF(ORCAMENTOS!R705="","",ORCAMENTOS!R705) -> -
L3190: =IF(ORCAMENTOS!R706="","",ORCAMENTOS!R706) -> -
